ash_dendro/__init__.py
ash_dendro/utils.py
ash_dendro-0.0.7.dist-info/LICENSE
ash_dendro-0.0.7.dist-info/METADATA
ash_dendro-0.0.7.dist-info/WHEEL
ash_dendro-0.0.7.dist-info/top_level.txt
ash_dendro-0.0.7.dist-info/RECORD
